fica/__init__.py
fica/config.py
fica/exporter.py
fica/key.py
fica/sphinx.py
fica/utils.py
fica/validators.py
fica/version.py
fica-0.4.1.dist-info/LICENSE
fica-0.4.1.dist-info/METADATA
fica-0.4.1.dist-info/WHEEL
fica-0.4.1.dist-info/RECORD
