Metadata-Version: 2.1
Name: fica
Version: 0.4.1
Summary: User configuration manager and documenter
Home-page: https://github.com/chrispyles/fica
License: MIT
Author: Chris Pyles
Author-email: cpyles@berkeley.edu
Requires-Python: >=3.9,<4.0
Classifier: License :: OSI Approved :: MIT License
Classifier: Operating System :: OS Independent
Classifier: Programming Language :: Python :: 3
Classifier: Programming Language :: Python :: 3.9
Classifier: Programming Language :: Python :: 3.10
Classifier: Programming Language :: Python :: 3.11
Classifier: Programming Language :: Python :: 3.12
Requires-Dist: docutils
Requires-Dist: pyyaml
Requires-Dist: sphinx
Project-URL: Documentation, https://fica.readthedocs.io/
Project-URL: Repository, https://github.com/chrispyles/fica
